{"name":"Hexo","postlist":[{"title":"阿里云搭建Git服务，实现Hexo自动部署","slug":"hexo-nginx-auto-deploy","date":"2016-03-03T08:33:19.000Z","updated":"2016-08-15T13:28:56.401Z","comments":true,"path":"api/articles/hexo-nginx-auto-deploy.json","excerpt":null,"keywords":null,"content":null,"raw":null,"categories":[],"tags":[{"name":"Hexo","path":"api/tags/Hexo.json"},{"name":"Nginx","path":"api/tags/Nginx.json"},{"name":"Linux","path":"api/tags/Linux.json"},{"name":"部署","path":"api/tags/部署.json"}]},{"title":"Hexo博客改版记录","slug":"hexo-blog-update-log","date":"2016-01-18T01:02:18.000Z","updated":"2016-08-15T13:28:56.401Z","comments":true,"path":"api/articles/hexo-blog-update-log.json","excerpt":null,"keywords":null,"content":null,"raw":null,"categories":[],"tags":[{"name":"Hexo","path":"api/tags/Hexo.json"},{"name":"material","path":"api/tags/material.json"}]},{"title":"Hexo添加站内搜索功能初步完成","slug":"hexo-search","date":"2016-05-11T08:08:50.000Z","updated":"2016-08-15T13:28:56.401Z","comments":true,"path":"api/articles/hexo-search.json","excerpt":null,"keywords":null,"content":null,"raw":null,"categories":[],"tags":[{"name":"Hexo","path":"api/tags/Hexo.json"}]},{"title":"Hexo添加Toc支持，生成文章目录","slug":"hexo-toc","date":"2015-05-14T07:25:47.000Z","updated":"2016-08-15T13:28:56.401Z","comments":true,"path":"api/articles/hexo-toc.json","excerpt":null,"keywords":null,"content":null,"raw":null,"categories":[],"tags":[{"name":"Hexo","path":"api/tags/Hexo.json"}]},{"title":"博客搬迁记 - 从WordPress到Hexo","slug":"wordpress-to-hexo","date":"2015-05-13T01:50:02.000Z","updated":"2016-08-15T13:28:56.417Z","comments":true,"path":"api/articles/wordpress-to-hexo.json","excerpt":null,"keywords":null,"content":null,"raw":null,"categories":[],"tags":[{"name":"Hexo","path":"api/tags/Hexo.json"},{"name":"WordPress","path":"api/tags/WordPress.json"},{"name":"gitcafe","path":"api/tags/gitcafe.json"}]}]}